{
  "359330668112642059": {
    "win": 0,
    "lose": 0,
    "point": 0,
    "max": 0,
    "min": 0
  },
  "193407417256640512": {
    "win": 3,
    "lose": 5,
    "point": -134,
    "max": 25,
    "min": -51
  },
  "559289569825259521": {
    "win": 4,
    "lose": 4,
    "point": 219,
    "max": 120,
    "min": -35
  },
  "713420616254095460": {
    "win": 0,
    "lose": 2,
    "point": -78,
    "max": 0,
    "min": -69
  },
  "703831366332317756": {
    "win": 0,
    "lose": 1,
    "point": -79,
    "max": 0,
    "min": -79
  },
  "713541431998021734": {
    "win": 0,
    "lose": 2,
    "point": -22,
    "max": 0,
    "min": -17
  },
  "598600835664183297": {
    "win": 0,
    "lose": 1,
    "point": -36,
    "max": 0,
    "min": -36
  },
  "731401718901899327": {
    "win": 1,
    "lose": 0,
    "point": 292,
    "max": 292,
    "min": 0
  },
  "582616639820922939": {
    "win": 0,
    "lose": 1,
    "point": -25,
    "max": 0,
    "min": -25
  },
  "573870933236776960": {
    "win": 0,
    "lose": 1,
    "point": -65,
    "max": 0,
    "min": -65
  },
  "662681692586246154": {
    "win": 0,
    "lose": 1,
    "point": -44,
    "max": 0,
    "min": -44
  },
  "700027069278716074": {
    "win": 0,
    "lose": 1,
    "point": -28,
    "max": 0,
    "min": -28
  }
}